{
  "version": 2,
  "projects": {
    "cli": "apps/cli",
    "electron": "apps/electron",
    "vscode": "apps/vscode",
    "api": "apps/api",
    "temporal": "apps/temporal",
    "planner-agent": "libs/agents/planner-agent",
    "coder-agent": "libs/agents/coder-agent",
    "critic-agent": "libs/agents/critic-agent",
    "reasoning-agent": "libs/agents/reasoning-agent",
    "search-agent": "libs/agents/search-agent",
    "feedback-agent": "libs/agents/feedback-agent",
    "project-mgr-agent": "libs/agents/project-mgr-agent",
    "explainability-agent": "libs/agents/explainability-agent",
    "memory-agent": "libs/agents/memory-agent",
    "observability-agent": "libs/agents/observability-agent",
    "model-adapter": "libs/adapters/model-adapter",
    "storage-adapter": "libs/adapters/storage-adapter",
    "observability-adapter": "libs/adapters/observability-adapter",
    "plugin-loader-adapter": "libs/adapters/plugin-loader-adapter",
    "reflexion-adapter": "libs/adapters/reflexion-adapter",
    "shared": "libs/shared",
    "ui": "libs/ui",
    "runtime": "libs/runtime",
    "context": "libs/context",
    "benchmark": "tools/benchmark",
    "migrations": "tools/migrations",
    "cache-warm": "tools/cache-warm",
    "rotate-keys": "tools/rotate-keys",
    "snapshot-chroma": "tools/snapshot-chroma",
    "example-plugin": "plugins/example-plugin",
    "another-plugin": "plugins/another-plugin"
  }
} 